SMAGrader/__init__.py
SMAGrader/checker.py
SMAGrader/constants.py
SMAGrader-0.1.11.dist-info/METADATA
SMAGrader-0.1.11.dist-info/WHEEL
SMAGrader-0.1.11.dist-info/top_level.txt
SMAGrader-0.1.11.dist-info/RECORD
