Metadata-Version: 2.1
Name: SMAGrader
Version: 0.1.11
Summary: Library for social media analysis course autograder
Author: arisharma
License: MIT
Requires-Dist: numpy
Requires-Dist: pandas
Requires-Dist: nltk
Requires-Dist: praw
